{
	"info": {
		"_postman_id": "99f4c43a-3018-4c62-ae38-75e5ec560bce",
		"name": "cursosBootcamp",
		"schema": "https://schema.getpostman.com/json/collection/v2.1.0/collection.json",
		"_exporter_id": "29198822"
	},
	"item": [
		{
			"name": "FIND ALL USUARIOS",
			"request": {
				"method": "GET",
				"header": [],
				"url": {
					"raw": "http://localhost:3000/api/usuarios",
					"protocol": "http",
					"host": [
						"localhost"
					],
					"port": "3000",
					"path": [
						"api",
						"usuarios"
					]
				}
			},
			"response": []
		},
		{
			"name": "FIND ALL BOOTCAMP",
			"request": {
				"method": "GET",
				"header": [],
				"url": {
					"raw": "http://localhost:3000/api/bootcamp/1",
					"protocol": "http",
					"host": [
						"localhost"
					],
					"port": "3000",
					"path": [
						"api",
						"bootcamp",
						"1"
					]
				}
			},
			"response": []
		},
		{
			"name": "CREATE BOOTCAMP",
			"request": {
				"method": "POST",
				"header": [],
				"body": {
					"mode": "urlencoded",
					"urlencoded": [
						{
							"key": "title",
							"value": "Bootcamp Big Data, Inteligencia Artificial & Machine Learning.",
							"type": "text"
						},
						{
							"key": "cue",
							"value": "18",
							"type": "text"
						},
						{
							"key": "description",
							"value": "Domina Data Science, y todo el ecosistema de lenguajes y herramientas de Big Data, e intégralos con modelos avanzados de Artificial Intelligence y Machine Learning.",
							"type": "text"
						}
					]
				},
				"url": {
					"raw": "http://localhost:3000/api/bootcamp",
					"protocol": "http",
					"host": [
						"localhost"
					],
					"port": "3000",
					"path": [
						"api",
						"bootcamp"
					],
					"query": [
						{
							"key": "",
							"value": null,
							"disabled": true
						}
					]
				}
			},
			"response": []
		},
		{
			"name": "FIND USUARIOS BY ID",
			"request": {
				"method": "GET",
				"header": [],
				"url": {
					"raw": "http://localhost:3000/api/usuarios/1",
					"protocol": "http",
					"host": [
						"localhost"
					],
					"port": "3000",
					"path": [
						"api",
						"usuarios",
						"1"
					]
				}
			},
			"response": []
		},
		{
			"name": "DELETE USUARIO",
			"request": {
				"method": "DELETE",
				"header": [],
				"url": {
					"raw": "http://localhost:3000/api/usuarios/1",
					"protocol": "http",
					"host": [
						"localhost"
					],
					"port": "3000",
					"path": [
						"api",
						"usuarios",
						"1"
					]
				}
			},
			"response": []
		},
		{
			"name": "UPDATE USUARIO",
			"request": {
				"method": "PUT",
				"header": [],
				"body": {
					"mode": "urlencoded",
					"urlencoded": [
						{
							"key": "firstName",
							"value": "Mateo",
							"type": "text"
						},
						{
							"key": "lastName",
							"value": "Diaz",
							"type": "text"
						}
					]
				},
				"url": {
					"raw": "http://localhost:3000/api/usuarios/1",
					"protocol": "http",
					"host": [
						"localhost"
					],
					"port": "3000",
					"path": [
						"api",
						"usuarios",
						"1"
					]
				}
			},
			"response": []
		},
		{
			"name": "UPDATE BOOTCAMP",
			"request": {
				"method": "PUT",
				"header": [],
				"body": {
					"mode": "urlencoded",
					"urlencoded": [
						{
							"key": "firstName",
							"value": "Mateo",
							"type": "text"
						}
					]
				},
				"url": {
					"raw": "http://localhost:3000/api/bootcamp/1",
					"protocol": "http",
					"host": [
						"localhost"
					],
					"port": "3000",
					"path": [
						"api",
						"bootcamp",
						"1"
					]
				}
			},
			"response": []
		},
		{
			"name": "CREATE USUARIOS",
			"request": {
				"method": "POST",
				"header": [],
				"body": {
					"mode": "raw",
					"raw": "\r\n\r\n    {\r\n     \"firstName\":\"Facundo\",\r\n    \"lastName\":\"Fernandez\",\r\n    \"email\":\"facundo.fernandez@correo.com\"\r\n\r\n    }\r\n   \r\n \r\n   ",
					"options": {
						"raw": {
							"language": "json"
						}
					}
				},
				"url": {
					"raw": "http://localhost:3000/api/usuarios",
					"protocol": "http",
					"host": [
						"localhost"
					],
					"port": "3000",
					"path": [
						"api",
						"usuarios"
					]
				}
			},
			"response": []
		},
		{
			"name": "VINCULAR USUARIO A BOOTCAMP",
			"request": {
				"method": "POST",
				"header": [],
				"body": {
					"mode": "urlencoded",
					"urlencoded": [
						{
							"key": "usuarioId",
							"value": "3",
							"type": "text"
						},
						{
							"key": "bootcampID",
							"value": "3",
							"type": "text"
						}
					]
				},
				"url": {
					"raw": "http://localhost:3000/api/bootcamp/adduser",
					"protocol": "http",
					"host": [
						"localhost"
					],
					"port": "3000",
					"path": [
						"api",
						"bootcamp",
						"adduser"
					]
				}
			},
			"response": []
		}
	]
}